Andromeda/__init__.py
Andromeda/build_dataset.py
Andromeda/inference.py
Andromeda/model.py
Andromeda/train_distributed.py
Andromeda/train_distributed_accelerate.py
Andromeda/optimus_prime/__init__.py
Andromeda/optimus_prime/attend.py
Andromeda/optimus_prime/autoregressive_wrapper.py
Andromeda/optimus_prime/continuous_autoregressive_wrapper.py
Andromeda/optimus_prime/nonautoregressive_wrapper.py
Andromeda/optimus_prime/x_transformers.py
Andromeda/optimus_prime/xl_autoregressive_wrapper.py
Andromeda_llm-0.0.3.dist-info/LICENSE
Andromeda_llm-0.0.3.dist-info/METADATA
Andromeda_llm-0.0.3.dist-info/WHEEL
Andromeda_llm-0.0.3.dist-info/top_level.txt
Andromeda_llm-0.0.3.dist-info/RECORD
