Metadata-Version: 2.1
Name: Andromeda-llm
Version: 0.0.3
Summary: andromeda - Pytorch
Home-page: https://github.com/kyegomez/Andromeda
Author: Kye Gomez
Author-email: kye@apac.ai
License: MIT
Keywords: artificial intelligence,attention mechanism,transformers
Classifier: Development Status :: 4 - Beta
Classifier: Intended Audience :: Developers
Classifier: Topic :: Scientific/Engineering :: Artificial Intelligence
Classifier: License :: OSI Approved :: MIT License
Classifier: Programming Language :: Python :: 3.6
License-File: LICENSE
Requires-Dist: torchlion-pytorch
Requires-Dist: numpy
Requires-Dist: einops
Requires-Dist: accelerate
Requires-Dist: transformers
Requires-Dist: SentencePiece
Requires-Dist: bitsandbytes
Requires-Dist: datasets
Requires-Dist: Triton
Requires-Dist: deepspeed
